<?xml version="1.0" encoding="UTF-8"?>
<monster name="Nekomancer" nameDescription="a nekomancer" race="blood" experience="5000" speed="200" manacost="0" script="catmage.lua">
        <health now="5000" max="5000"/>
        <look type="324" head="0" body="114" legs="90" feet="0" addons="1" corpse="20368"/>
        <targetchange interval="4000" chance="10"/>
        <flags>
                <flag summonable="0"/>
                <flag attackable="1"/>
                <flag hostile="1"/>
                <flag illusionable="0"/>
                <flag convinceable="0"/>
                <flag pushable="0"/>
                <flag canpushitems="1"/>
                <flag canpushcreatures="1"/>
                <flag targetdistance="4"/>
                <flag staticattack="90"/>
                <flag runonhealth="0"/>
        </flags>
        <attacks>
                <!-- ai -->
        </attacks>
        <defenses armor="25" defense="25">
                <defense name="healing" interval="2000" chance="15" min="50" max="300">
                        <attribute key="areaEffect" value="blueshimmer"/>
                </defense>
        </defenses>
        <elements>
                <element energyPercent="-25"/>
                <element earthPercent="70"/>
                <element deathPercent="50"/>
                <element physicalPercent="-25"/>
                <element firePercent="70"/>
                <element icePercent="-25"/>
                <element holyPercent="-25"/>
        </elements>
        <immunities>
                <immunity invisible="1"/>
                <immunity drown="1"/>
        </immunities>
        <loot>
                <item id="2148" countmax="100" chance="35000"/> <!-- gold coin -->
                <item id="2148" countmax="100" chance="35000"/> <!-- gold coin -->
                <item id="2148" countmax="100" chance="35000"/> <!-- gold coin -->
                <item id="2152" countmax="50" chance="3000"/> <!-- platinum coin -->
                <item id="2160" countmax="5" chance="700"/> <!-- crystal coin -->
 
                <item id="13297" countmax="2" chance="1000"/> <!-- haunch of boar -->
                <item id="2666" countmax="5" chance="10000"/> <!-- meat -->
                <item id="2667" countmax="5" chance="10000"/> <!-- fish -->
                <item id="2671" countmax="5" chance="3000"/> <!-- ham -->
                <item id="2668" countmax="5" chance="10000"/> <!-- salmon -->
               
                <item id="11209" chance="9000"/> <!-- silky fur -->
                <item id="12431" chance="9000"/> <!-- necromantic robe -->
                <item id="11324" chance="9000"/> <!-- shaggy tail -->
                <item id="13027" chance="700"/> <!-- panther paw -->
               
                <item id="6558" chance="6000"/> <!-- concentrated demonic blood -->
                <item id="7590" countmax="2" chance="1000"/> <!-- great mana potion -->
                <item id="7589" countmax="2" chance="4000"/> <!-- strong mana potion -->
                <item id="7620" countmax="2" chance="6000"/> <!-- mana potion -->
                <item id="7588" countmax="2" chance="6000"/> <!-- strong health potion -->
                <item id="7618" countmax="2" chance="4000"/> <!-- health potion -->
                <item id="7440" countmax="2" chance="1000"/> <!-- mastermind potion -->
                <item id="8472" countmax="2" chance="1000"/> <!-- great spirit potion -->
               
                <item id="6500" chance="9000"/> <!-- demonic essence -->
                <item id="5944" chance="15000"/> <!-- soul orb -->
               
                <item id="2151" countmax="3" chance="400"/> <!-- talon -->
                <item id="2150" countmax="4" chance="900"/> <!-- small amethyst -->
                <item id="2147" countmax="4" chance="900"/> <!-- small ruby -->
                <item id="9971" countmax="2" chance="300"/> <!-- gold ingot -->
                <item id="2144" countmax="5" chance="1000"/> <!-- black pearl -->
                <item id="2143" countmax="5" chance="900"/> <!-- white pearl -->
                <item id="9970" countmax="5" chance="900"/> <!-- small topaz -->
                <item id="7762" countmax="4" chance="900"/> <!-- small enchanted amethyst -->
                <item id="7760" countmax="4" chance="900"/> <!-- small enchanted ruby -->
               
                <item id="2231" chance="15000"/> <!-- big bone -->
                <item id="2230" chance="15000"/> <!-- bone -->
                <item id="2227" chance="15000"/> <!-- rotten meat -->
 
                <item id="2661" chance="4000"/> <!-- scarf -->
                <item id="2171" chance="1000"/> <!-- platinum amulet -->
                <item id="2197" chance="1000"/> <!-- stone skin amulet -->
                <item id="2198" chance="1000"/> <!-- elven amulet -->
                <item id="2168" chance="1000"/> <!-- life ring -->
                <item id="2169" chance="1000"/> <!-- time ring -->
                <item id="2165" chance="1000"/> <!-- stealth ring -->
                <item id="2214" chance="1000"/> <!-- ring of healing -->
                <item id="2164" chance="1000"/> <!-- might ring -->
                <item id="5468" chance="1500"/> <!-- fire bug -->
                <item id="7890" chance="1000"/> <!-- magma amulet -->
                <item id="2412" chance="3000"/> <!-- katana -->
                <item id="2419" chance="1000"/> <!-- scimitar -->
                <item id="2420" chance="3000"/> <!-- machete -->       
                <item id="8892" chance="1500"/> <!-- ethno coat -->
                <item id="7457" chance="1000"/> <!-- fur boots -->
                <item id="2323" chance="1000"/> <!-- hat of the mad -->
                <item id="2662" chance="1000"/> <!-- magician hat -->
                <item id="2457" chance="3000"/> <!-- steel helmet -->
                <item id="2515" chance="1000"/> <!-- guardian shield -->
                <item id="2033" chance="1500"/> <!-- golden mug -->
                <item id="2260" chance="1500"/> <!-- blank rune -->
                <item id="2449" chance="1500"/> <!-- bone club -->
               
                <item id="2179" chance="300"/> <!-- gold ring -->
                <item id="10218" chance="300"/> <!-- bonfire amulet -->
                <item id="10221" chance="300"/> <!-- shockwave amulet -->
                <item id="7408" chance="300"/> <!-- wyvern fang -->
                <item id="7424" chance="300"/> <!-- lunar staff -->
                <item id="2189" chance="300"/> <!-- wand of cosmic energy -->
                <item id="2392" chance="300"/> <!-- fire sword -->
                <item id="2497" chance="300"/> <!-- crusader helmet -->
                <item id="7900" chance="300"/> <!-- magma monocle -->
                <item id="2491" chance="300"/> <!-- crown helmet -->
                <item id="8871" chance="300"/> <!-- focus cape -->
               
                <item id="12608" chance="120"/> <!-- broken key ring -->
                <item id="7426" chance="120"/> <!-- amber staff -->
                <item id="7456" chance="120"/> <!-- noble axe -->
                <item id="8920" chance="120"/> <!-- wand of starstorm -->
                <item id="2438" chance="120"/> <!-- epee -->
                <item id="2184" chance="120"/> <!-- crystal wand -->
               
                <item id="7386" chance="80"/> <!-- mercenary sword -->
                <item id="8902" chance="80"/> <!-- spellbook of mind control -->
                <item id="7404" chance="80"/> <!-- assassin dagger -->
                <item id="2466" chance="80"/> <!-- golden armor -->
                <item id="7899" chance="80"/> <!-- magma coat -->
                <item id="2487" chance="80"/> <!-- crown armor -->
                <item id="2470" chance="80"/> <!-- golden legs -->
                <item id="7894" chance="80"/> <!-- magma legs -->
                <item id="2488" chance="80"/> <!-- crown legs -->
                <item id="2414" chance="80"/> <!-- dragon lance -->
                <item id="2427" chance="80"/> <!-- guardian halberd -->
                <item id="7891" chance="80"/> <!-- magma boots -->
               
                <item id="5480" chance="60"/> <!-- cat's paw -->
                <item id="2123" chance="60"/> <!-- ring of the sky -->
                <item id="10570" chance="60"/> <!-- witch hat -->
                <item id="8855" chance="60"/> <!-- composite hornbow -->
                <item id="7391" chance="60"/> <!-- thaian sword -->    
                <item id="2514" chance="60"/> <!-- mastermind shield -->
                <item id="2195" chance="60"/> <!-- boots of haste -->
                <item id="5884" chance="60"/> <!-- spirit container -->
                <item id="5904" chance="60"/> <!-- magic sulphur -->
                <item id="5891" chance="60"/> <!-- enchanted chicken wing -->
               
                <item id="8305" chance="50"/> <!-- mother soil -->
                <item id="8298" chance="50"/> <!-- natural soil -->
                <item id="8299" chance="50"/> <!-- glimmering soil -->
                <item id="8310" chance="50"/> <!-- neutral matter -->
                <item id="8301" chance="50"/> <!-- holy soil -->
                <item id="8300" chance="50"/> <!-- flawless ice crystal -->
                <item id="11227" chance="50"/> <!-- shiny stone -->
                <item id="11339" chance="50"/> <!-- clay lump -->
                <item id="18423" chance="50"/> <!-- major crystalline token -->
                <item id="18422" chance="50"/> <!-- minor crystalline token -->
                <item id="7633" chance="50"/> <!-- giant shimmering pearl -->
                <item id="7632" chance="50"/> <!-- giant shimmering pearl -->
                <item id="2361" chance="50"/> <!-- frozen starlight -->
                <item id="9742" chance="50"/> <!-- charged ghost charm -->
                <item id="22396" chance="50"/> <!-- cluster of solace -->
                <item id="2153" chance="50"/> <!-- violet gem -->
                <item id="7735" chance="50"/> <!-- spellwand -->
               
                <item id="13293" chance="40"/> <!-- leather whip -->
                <item id="2539" chance="40"/> <!-- phoenix shield -->
                <item id="7431" chance="40"/> <!-- demonbone -->
                <item id="2453" chance="40"/> <!-- arcane staff -->
                <item id="8885" chance="40"/> <!-- divine plate -->
                <item id="2355" chance="40"/> <!-- stuffed bunny -->
                <item id="5791" chance="40"/> <!-- stuffed dragon -->
                <item id="5080" chance="40"/> <!-- panda teddy -->
               
                <item id="15545" chance="10"/> <!-- foxtail -->
                <item id="9006" chance="10"/> <!-- toy spider -->
                <item id="22397" chance="10"/> <!-- dream matter -->
        </loot>
</monster>